lib_config/__init__.py
lib_config/config.py
lib_config/tests/__init__.py
lib_config/tests/conftest.py
lib_config/tests/test_config.py
lib_config-0.1.2.dist-info/AUTHORS
lib_config-0.1.2.dist-info/LICENSE
lib_config-0.1.2.dist-info/METADATA
lib_config-0.1.2.dist-info/WHEEL
lib_config-0.1.2.dist-info/top_level.txt
lib_config-0.1.2.dist-info/RECORD
