Metadata-Version: 2.1
Name: lib-config
Version: 0.1.2
Summary: UNKNOWN
Home-page: https://github.com/jfuruness/lib_config.git
Author: Justin Furuness
Author-email: jfuruness@gmail.com
License: UNKNOWN
Download-URL: https://github.com/jfuruness/lib_config.git
Keywords: Furuness,Config,Wrapper,ETL,Helper Functions
Platform: UNKNOWN
Classifier: Environment :: Console
Classifier: Intended Audience :: Developers
Classifier: License :: OSI Approved :: BSD License
Classifier: Programming Language :: Python :: 3
Requires-Dist: lib-utils
Requires-Dist: pytest
